django_microservices_package/__init__.py
django_microservices_package/call_endpoint.py
microservices_django-0.0.1.dist-info/LICENSE
microservices_django-0.0.1.dist-info/METADATA
microservices_django-0.0.1.dist-info/WHEEL
microservices_django-0.0.1.dist-info/top_level.txt
microservices_django-0.0.1.dist-info/RECORD
