Metadata-Version: 2.1
Name: microservices_django
Version: 0.0.1
Summary: A Django package for microservices
Home-page: https://github.com/rimalsparsha/Django_microservices.git
Author: Sparsha Rimal
Author-email: sparsharimal@gmail.com
License: MIT License
Classifier: Environment :: Web Environment
Classifier: Framework :: Django
Classifier: Intended Audience :: Developers
Classifier: License :: OSI Approved :: MIT License
Classifier: Operating System :: OS Independent
Classifier: Programming Language :: Python
Classifier: Programming Language :: Python :: 3
Classifier: Framework :: Django :: 3.2
License-File: LICENSE
Requires-Dist: Django >=3.2
